audible_series/__init__.py
audible_series/cmd_series.py
audible_series/configfile.py
audible_series/seriesutil.py
audible_series-1.1.0.dist-info/LICENSE
audible_series-1.1.0.dist-info/METADATA
audible_series-1.1.0.dist-info/WHEEL
audible_series-1.1.0.dist-info/entry_points.txt
audible_series-1.1.0.dist-info/RECORD
