Metadata-Version: 2.1
Name: audible-series
Version: 1.1.0
Summary: Adds a command to audible-cli that looks for new series releases in a user's library.
Home-page: https://github.com/luscoma/audible-series
Keywords: audible
Author: Alex Lusco
Author-email: alex.lusco@gmail.com
Requires-Python: >=3.8,<3.12
Classifier: Programming Language :: Python :: 3
Classifier: Programming Language :: Python :: 3.8
Classifier: Programming Language :: Python :: 3.9
Classifier: Programming Language :: Python :: 3.10
Classifier: Programming Language :: Python :: 3.11
Requires-Dist: audible (>=0.9.1,<0.10.0)
Requires-Dist: pyyaml (>=6.0.1,<7.0.0)
Project-URL: Repository, https://github.com/luscoma/audible-series
